odoo/addons/product_sale_team/README.rst
odoo/addons/product_sale_team/__init__.py
odoo/addons/product_sale_team/__manifest__.py
odoo/addons/product_sale_team/i18n/it.po
odoo/addons/product_sale_team/i18n/product_sale_team.pot
odoo/addons/product_sale_team/models/__init__.py
odoo/addons/product_sale_team/models/product_template.py
odoo/addons/product_sale_team/readme/CONTEXT.md
odoo/addons/product_sale_team/readme/CONTRIBUTORS.md
odoo/addons/product_sale_team/readme/CREDITS.md
odoo/addons/product_sale_team/readme/DESCRIPTION.md
odoo/addons/product_sale_team/readme/USAGE.md
odoo/addons/product_sale_team/static/description/icon.png
odoo/addons/product_sale_team/static/description/index.html
odoo/addons/product_sale_team/tests/__init__.py
odoo/addons/product_sale_team/tests/test_product_sale_team.py
odoo/addons/product_sale_team/views/product_template_views.xml
odoo_addon_product_sale_team-18.0.1.0.0.4.dist-info/METADATA
odoo_addon_product_sale_team-18.0.1.0.0.4.dist-info/WHEEL
odoo_addon_product_sale_team-18.0.1.0.0.4.dist-info/top_level.txt
odoo_addon_product_sale_team-18.0.1.0.0.4.dist-info/RECORD
